qc_otx/__init__.py
qc_otx/__main__.py
qc_otx/checks/__init__.py
qc_otx/checks/core_checker/__init__.py
qc_otx/checks/core_checker/document_name_matches_filename.py
qc_otx/checks/core_checker/document_name_package_uniqueness.py
qc_otx/checks/core_checker/have_specification_if_no_realisation_exists.py
qc_otx/checks/core_checker/mandatory_constant_initialization.py
qc_otx/checks/core_checker/match_of_imported_document_data_model_version.py
qc_otx/checks/core_checker/no_dead_import_links.py
qc_otx/checks/core_checker/no_unused_imports.py
qc_otx/checks/core_checker/no_use_of_undefined_import_prefixes.py
qc_otx/checks/core_checker/public_main_procedure.py
qc_otx/checks/core_checker/unique_node_names.py
qc_otx/checks/data_type_checker/__init__.py
qc_otx/checks/data_type_checker/accessing_structure_elements.py
qc_otx/checks/data_type_checker/correct_target_for_structure_element.py
qc_otx/checks/models.py
qc_otx/checks/state_machine_checker/__init__.py
qc_otx/checks/state_machine_checker/distinguished_initial_and_completed_state.py
qc_otx/checks/state_machine_checker/mandatory_target_state.py
qc_otx/checks/state_machine_checker/mandatory_transition.py
qc_otx/checks/state_machine_checker/mandatory_trigger.py
qc_otx/checks/state_machine_checker/no_procedure_realization.py
qc_otx/checks/state_machine_checker/no_target_state_for_completed_state.py
qc_otx/checks/utils.py
qc_otx/checks/zip_file_checker/__init__.py
qc_otx/checks/zip_file_checker/type_safe_unzip_file.py
qc_otx/checks/zip_file_checker/type_safe_zip_file.py
qc_otx/constants.py
qc_otx/main.py
asam_qc_otx-1.0.0.dist-info/LICENSE
asam_qc_otx-1.0.0.dist-info/LICENSES/3rd_party_terms_and_licenses/Black_LICENSE
asam_qc_otx-1.0.0.dist-info/LICENSES/3rd_party_terms_and_licenses/Lxml_LICENSE
asam_qc_otx-1.0.0.dist-info/LICENSES/3rd_party_terms_and_licenses/Pytest_LICENSE
asam_qc_otx-1.0.0.dist-info/LICENSES/readme.md
asam_qc_otx-1.0.0.dist-info/METADATA
asam_qc_otx-1.0.0.dist-info/WHEEL
asam_qc_otx-1.0.0.dist-info/entry_points.txt
asam_qc_otx-1.0.0.dist-info/RECORD
